ec_promethee/__init__.py
ec_promethee/algorithm/__init__.py
ec_promethee/algorithm/src.py
ec_promethee-1.2.0.dist-info/LICENSE
ec_promethee-1.2.0.dist-info/METADATA
ec_promethee-1.2.0.dist-info/WHEEL
ec_promethee-1.2.0.dist-info/top_level.txt
ec_promethee-1.2.0.dist-info/RECORD
