Metadata-Version: 2.1
Name: ec-promethee
Version: 1.2.0
Summary: The EC-PROMETHEE Method - A Committee Approach for Outranking Problems Using Randoms Weights
Home-page: https://github.com/Valdecy/ec_promethee
Author: Valdecy Pereira
Author-email: valdecy.pereira@gmail.com
License: GNU
License-File: LICENSE
Requires-Dist: matplotlib
Requires-Dist: numpy
Requires-Dist: pandas
Requires-Dist: scikit-learn
Requires-Dist: scipy
Requires-Dist: seaborn
